datatap/__init__.py
datatap/py.typed
datatap/api/__init__.py
datatap/api/endpoints/__init__.py
datatap/api/endpoints/database_endpoints.py
datatap/api/endpoints/dataset_endpoints.py
datatap/api/endpoints/endpoints.py
datatap/api/endpoints/repository_endpoints.py
datatap/api/endpoints/request.py
datatap/api/endpoints/user_endpoints.py
datatap/api/entities/__init__.py
datatap/api/entities/api.py
datatap/api/entities/database.py
datatap/api/entities/dataset.py
datatap/api/entities/repository.py
datatap/api/entities/user.py
datatap/api/types/__init__.py
datatap/api/types/database.py
datatap/api/types/dataset.py
datatap/api/types/repository.py
datatap/api/types/user.py
datatap/comet/__init__.py
datatap/droplet/__init__.py
datatap/droplet/_media.py
datatap/droplet/attributes.py
datatap/droplet/bounding_box.py
datatap/droplet/class_annotation.py
datatap/droplet/frame_annotation.py
datatap/droplet/image.py
datatap/droplet/image_annotation.py
datatap/droplet/instance.py
datatap/droplet/keypoint.py
datatap/droplet/multi_instance.py
datatap/droplet/segmentation.py
datatap/droplet/video.py
datatap/droplet/video_annotation.py
datatap/examples/__init__.py
datatap/geometry/__init__.py
datatap/geometry/mask.py
datatap/geometry/point.py
datatap/geometry/polygon.py
datatap/geometry/rectangle.py
datatap/metrics/__init__.py
datatap/metrics/_types.py
datatap/metrics/confusion_matrix.py
datatap/metrics/iou.py
datatap/metrics/precision_recall_curve.py
datatap/template/__init__.py
datatap/template/class_annotation_template.py
datatap/template/frame_annotation_template.py
datatap/template/image_annotation_template.py
datatap/template/instance_template.py
datatap/template/multi_instance_template.py
datatap/template/video_annotation_template.py
datatap/tf/__init__.py
datatap/tf/dataset.py
datatap/torch/__init__.py
datatap/torch/_patch_torch.py
datatap/torch/dataloader.py
datatap/torch/dataset.py
datatap/torch/utils.py
datatap/utils/__init__.py
datatap/utils/cache_generator.py
datatap-0.3.0.dist-info/LICENSE
datatap-0.3.0.dist-info/METADATA
datatap-0.3.0.dist-info/WHEEL
datatap-0.3.0.dist-info/dependency_links.txt
datatap-0.3.0.dist-info/top_level.txt
datatap-0.3.0.dist-info/RECORD
