Metadata-Version: 2.1
Name: datatap
Version: 0.3.0
Summary: Client library for dataTap
Home-page: https://github.com/zensors/datatap-python
Author: Zensors' Dev Team
Author-email: dev-team@zensors.com
License: UNKNOWN
Platform: UNKNOWN
Classifier: Programming Language :: Python :: 3
Classifier: Operating System :: OS Independent
Classifier: License :: OSI Approved :: GNU General Public License v3 (GPLv3)
Requires-Python: >=3.7
Requires-Dist: boto3 (>=1.15.14)
Requires-Dist: fastjsonschema (==2.14.2)
Requires-Dist: toolz (>=0.10.0)
Requires-Dist: simplejson (>=3.17.0)
Requires-Dist: jsonmerge (==1.7.0)
Requires-Dist: neo4j (==4.0.1)
Requires-Dist: Shapely
Requires-Dist: requests (>=2.23.0)
Requires-Dist: typing-extensions
Provides-Extra: image
Requires-Dist: palettable (>=3.3.0) ; extra == 'image'
Requires-Dist: Flask (>=1.1.1) ; extra == 'image'
Requires-Dist: Pillow (>=7.1.0) ; extra == 'image'
Requires-Dist: Shapely (>=1.7.0) ; extra == 'image'
Requires-Dist: scipy (>=1.4.1) ; extra == 'image'
Requires-Dist: importlib-resources (>=1.4.0) ; extra == 'image'
Requires-Dist: boto3 (>=1.15.14) ; extra == 'image'
Provides-Extra: importers
Requires-Dist: Shapely (==1.7.0) ; extra == 'importers'
Requires-Dist: scikit-image (==0.17.2) ; extra == 'importers'
Requires-Dist: Unidecode (==1.1.1) ; extra == 'importers'
Provides-Extra: metrics
Requires-Dist: numpy (>=1.19.2) ; extra == 'metrics'
Requires-Dist: sortedcontainers (>=0.8.1) ; extra == 'metrics'
Requires-Dist: matplotlib (>=3.3.2) ; extra == 'metrics'
Requires-Dist: scipy (>=1.5.2) ; extra == 'metrics'
Provides-Extra: tf
Requires-Dist: tensorflow (>=2.0.0) ; extra == 'tf'
Provides-Extra: torch
Requires-Dist: torch (>=1.8.0+cpu) ; extra == 'torch'
Requires-Dist: torchvision (>=0.9.0+cpu) ; extra == 'torch'
